mobio/libs/schedule/__init__.py
mobio/libs/schedule/utils.py
m_schedule-1.0.1.dist-info/METADATA
m_schedule-1.0.1.dist-info/WHEEL
m_schedule-1.0.1.dist-info/top_level.txt
m_schedule-1.0.1.dist-info/RECORD
