Metadata-Version: 2.1
Name: m-schedule
Version: 1.0.1
Summary: Tạo schedule chạy theo lịch
Home-page: https://github.com/mobiovn
Author: MOBIO
Author-email: contact@mobio.vn
License: MIT
Platform: UNKNOWN
Requires-Dist: m-singleton
Requires-Dist: schedule
Requires-Dist: m-threadpool
Requires-Dist: redis
Requires-Dist: python-dateutil
Requires-Dist: unidecode
